aiohttp_sqlalchemy/__init__.py
aiohttp_sqlalchemy/constants.py
aiohttp_sqlalchemy/decorators.py
aiohttp_sqlalchemy/exceptions.py
aiohttp_sqlalchemy/middlewares.py
aiohttp_sqlalchemy/py.typed
aiohttp_sqlalchemy/typedefs.py
aiohttp_sqlalchemy/utils.py
aiohttp_sqlalchemy/web_handlers.py
aiohttp_sqlalchemy-1.1.1.dist-info/LICENSE
aiohttp_sqlalchemy-1.1.1.dist-info/METADATA
aiohttp_sqlalchemy-1.1.1.dist-info/WHEEL
aiohttp_sqlalchemy-1.1.1.dist-info/RECORD
