Metadata-Version: 2.3
Name: aiohttp-sqlalchemy
Version: 1.1.1
Summary: SQLAlchemy 2.0 support for aiohttp.
License: MIT
Keywords: aiohttp,sqlalchemy,asyncio
Author: Ruslan Ilyasovich Gilfanov
Author-email: ri.gilfanov@yandex.ru>
Maintainer: Ruslan Ilyasovich Gilfanov
Maintainer-email: ri.gilfanov@yandex.ru>
Requires-Python: >=3.9,<3.14
Classifier: Development Status :: 5 - Production/Stable
Classifier: Framework :: aiohttp
Classifier: Framework :: AsyncIO
Classifier: License :: OSI Approved :: MIT License
Classifier: Operating System :: OS Independent
Classifier: Programming Language :: Python
Classifier: Programming Language :: Python :: 3
Classifier: Programming Language :: Python :: 3.9
Classifier: Programming Language :: Python :: 3.10
Classifier: Programming Language :: Python :: 3.11
Classifier: Programming Language :: Python :: 3.12
Classifier: Programming Language :: Python :: 3.13
Classifier: Topic :: Database
Classifier: Topic :: Database :: Front-Ends
Classifier: Topic :: Internet
Classifier: Topic :: Internet :: WWW/HTTP
Classifier: Topic :: Software Development
Classifier: Topic :: Software Development :: Libraries
Classifier: Topic :: Software Development :: Libraries :: Python Modules
Classifier: Typing :: Typed
Provides-Extra: mysql
Provides-Extra: postgresql
Provides-Extra: sqlite
Requires-Dist: aiohttp-things (>=1.1.1,<2)
Requires-Dist: aiomysql (>=0.2.0,<1) ; extra == "mysql"
Requires-Dist: aiosqlite (>=0.21.0,<1) ; extra == "sqlite"
Requires-Dist: asyncpg (>=0.30.0,<1) ; extra == "postgresql"
Requires-Dist: sqlalchemy-things (>=1.1.1,<2)
